{
  "lookup": {
    "rules": {
      "[{\"prev_action\": {\"action_name\": \"action_listen\"}, \"user\": {\"intent\": \"goodbye\"}}]": "utter_goodbye",
      "[{\"prev_action\": {\"action_name\": \"action_listen\"}, \"user\": {\"intent\": \"goodbye\"}}, {\"prev_action\": {\"action_name\": \"utter_goodbye\"}, \"user\": {\"intent\": \"goodbye\"}}]": "action_listen",
      "[{\"prev_action\": {\"action_name\": \"action_listen\"}, \"user\": {\"intent\": \"provide_subscription\"}}]": "utter_provide_subscription",
      "[{\"prev_action\": {\"action_name\": \"action_listen\"}, \"user\": {\"intent\": \"provide_subscription\"}}, {\"prev_action\": {\"action_name\": \"utter_provide_subscription\"}, \"user\": {\"intent\": \"provide_subscription\"}}]": "action_subscription_provide",
      "[{\"prev_action\": {\"action_name\": \"action_listen\"}, \"user\": {\"intent\": \"provide_subscription\"}}, {\"prev_action\": {\"action_name\": \"utter_provide_subscription\"}, \"user\": {\"intent\": \"provide_subscription\"}}, {\"prev_action\": {\"action_name\": \"action_subscription_provide\"}, \"user\": {\"intent\": \"provide_subscription\"}}]": "simple_music_form",
      "[{\"prev_action\": {\"action_name\": \"action_listen\"}, \"user\": {\"intent\": \"provide_subscription\"}}, {\"prev_action\": {\"action_name\": \"utter_provide_subscription\"}, \"user\": {\"intent\": \"provide_subscription\"}}, {\"prev_action\": {\"action_name\": \"action_subscription_provide\"}, \"user\": {\"intent\": \"provide_subscription\"}}, {\"active_loop\": {\"name\": \"simple_music_form\"}, \"prev_action\": {\"action_name\": \"simple_music_form\"}, \"user\": {\"intent\": \"provide_subscription\"}}]": "action_listen",
      "[{\"prev_action\": {\"action_name\": \"action_listen\"}, \"user\": {\"intent\": \"bot_challenge\"}}]": "utter_iamabot",
      "[{\"prev_action\": {\"action_name\": \"action_listen\"}, \"user\": {\"intent\": \"bot_challenge\"}}, {\"prev_action\": {\"action_name\": \"utter_iamabot\"}, \"user\": {\"intent\": \"bot_challenge\"}}]": "action_listen",
      "[{\"active_loop\": {\"name\": \"should_not_be_set\"}, \"prev_action\": {\"action_name\": \"simple_music_form\"}}]": "utter_music_slots",
      "[{\"active_loop\": {\"name\": \"should_not_be_set\"}, \"prev_action\": {\"action_name\": \"simple_music_form\"}}, {\"active_loop\": {\"name\": \"should_not_be_set\"}, \"prev_action\": {\"action_name\": \"utter_music_slots\"}}]": "action_listen"
    },
    "rule_only_slots": [],
    "rule_only_loops": [
      "simple_music_form"
    ],
    "rules_for_loop_unhappy_path": {
      "[{\"prev_action\": {\"action_name\": \"action_subscription_provide\"}}, {\"active_loop\": {\"name\": \"simple_music_form\"}, \"prev_action\": {\"action_name\": \"simple_music_form\"}, \"user\": {\"intent\": \"provide_subscription\"}}]": "do_not_predict_loop_action"
    },
    "rules_not_in_stories": [
      "predicting default action with intent session_start",
      "[{\"prev_action\": {\"action_name\": \"action_listen\"}, \"user\": {\"intent\": \"goodbye\"}}]",
      "handling active loops and forms - simple_music_form - action_listen",
      "[{\"prev_action\": {\"action_name\": \"action_listen\"}, \"user\": {\"intent\": \"bot_challenge\"}}, {\"prev_action\": {\"action_name\": \"utter_iamabot\"}, \"user\": {\"intent\": \"bot_challenge\"}}]",
      "[{\"prev_action\": {\"action_name\": \"action_listen\"}, \"user\": {\"intent\": \"bot_challenge\"}}]",
      "handling active loops and forms - simple_music_form",
      "[{\"prev_action\": {\"action_name\": \"action_listen\"}, \"user\": {\"intent\": \"goodbye\"}}, {\"prev_action\": {\"action_name\": \"utter_goodbye\"}, \"user\": {\"intent\": \"goodbye\"}}]",
      "predicting default action with intent restart",
      "predicting default action with intent back"
    ]
  }
}